{
"name":"移动MM",
"packageChannel":"mm5",
"comSec":"6a8802c99d7dd56e01045047ab79a41e",
"sdkJavaName":"com.ziplinegames.moai.CommonMMSMS",
"mainActivity":"com.x3gu.gbo.GboActivity",
"sdkDataJavaName":"com.ziplinegames.moai.Moaidataeye",
"appid":"300009147451",
"appkey":"6402C3782E189C292A297C74EA3E2F9F",
"dataAppid":"77A0F8031B9CAA2D9AFE38CC237B26DA",
"dataChannel":"4399-MMSMS",
"channelId":"0",
"copGameId":"53",
"copChannelId":"195",
"channelName":"MMSMS",
"cdkChannel":"2196",
"sdkAdvJavaName":"com.ziplinegames.moai.Moaidomob",
"PublisherID":"96ZJ2vlgzeHxrwTBHE",
"mmsmsValiUrl":"http://mmsms.ultralisk.cn/api/mmquery.php",
"payCodes":[
{"number":"1","money":3000,"payCode":"30000914745101"},
{"number":"2","money":600,"payCode":"30000914745102"},
{"number":"3","money":2800,"payCode":"30000914745103"},
{"number":"4","money":1800,"payCode":"30000914745104"},
{"number":"5","money":600,"payCode":"30000914745105"},
{"number":"6","money":1500,"payCode":"30000914745106"},
{"number":"7","money":3000,"payCode":"30000914745107"},
{"number":"8","money":3000,"payCode":"30000914745108"},
{"number":"9","money":2800,"payCode":"30000914745109"},
{"number":"10","money":600,"payCode":"30000914745110"},
{"number":"11","money":600,"payCode":"30000914745111"},
{"number":"12","money":2800,"payCode":"30000914745112"},
{"number":"13","money":600,"payCode":"30000914745113"},
{"number":"14","money":1000,"payCode":"30000914745114"},
{"number":"15","money":600,"payCode":"30000914745115"},
{"number":"16","money":800,"payCode":"30000914745116"},
{"number":"17","money":1200,"payCode":"30000914745117"},
{"number":"18","money":1800,"payCode":"30000914745118"},
{"number":"19","money":1000,"payCode":"30000914745119"},
{"number":"20","money":600,"payCode":"30000914745120"},
{"number":"21","money":1500,"payCode":"30000914745121"},
{"number":"22","money":1500,"payCode":"30000914745122"},
{"number":"23","money":1500,"payCode":"30000914745123"},
{"number":"24","money":1500,"payCode":"30000914745124"},
{"number":"25","money":2000,"payCode":"30000914745125"},
{"number":"26","money":2000,"payCode":"30000914745126"},
{"number":"27","money":1000,"payCode":"30000914745127"},
{"number":"28","money":3000,"payCode":"30000914745128"},
{"number":"29","money":3000,"payCode":"30000914745129"},
{"number":"30","money":1500,"payCode":"30000914745130"}
]
}